feagi_connector_video_capture/__init__.py
feagi_connector_video_capture/__main__.py
feagi_connector_video_capture/controller.py
feagi_connector_video_capture/version.py
feagi_connector_video_capture-0.0.1.dist-info/LICENSE
feagi_connector_video_capture-0.0.1.dist-info/METADATA
feagi_connector_video_capture-0.0.1.dist-info/WHEEL
feagi_connector_video_capture-0.0.1.dist-info/top_level.txt
feagi_connector_video_capture-0.0.1.dist-info/RECORD
