Metadata-Version: 2.1
Name: feagi_connector_video_capture
Version: 0.0.1
Summary: Feagi agent video capture to connect feagi with your video capture
Home-page: https://github.com/feagi/feagi
Author: Neuraville INC
Author-email: info@neuraville.com
Project-URL: Bug Tracker, https://github.com/feagi/feagi/issues
Classifier: Programming Language :: Python :: 3 :: Only
Classifier: License :: OSI Approved :: Apache Software License
Classifier: Operating System :: OS Independent
Requires-Python: >=3.6
License-File: LICENSE
Requires-Dist: feagi-connector
Requires-Dist: pyzmq>=22.3.0
Requires-Dist: Pillow==10.1.0
Requires-Dist: mss==9.0.1
Requires-Dist: screeninfo==0.8.1
Requires-Dist: zmq>=0.0.0; python_version < "3.8"
